pushoverflow/VERSION
pushoverflow/__init__.py
pushoverflow/cli.py
pushoverflow/core.py
pushoverflow/stack_exchange.py
pushoverflow-2.0.1.dist-info/LICENSE
pushoverflow-2.0.1.dist-info/METADATA
pushoverflow-2.0.1.dist-info/WHEEL
pushoverflow-2.0.1.dist-info/entry_points.txt
pushoverflow-2.0.1.dist-info/top_level.txt
pushoverflow-2.0.1.dist-info/RECORD
