Metadata-Version: 2.1
Name: pushoverflow
Version: 2.0.1
Summary: Pushover Notifications for StackExchange Sites
Home-page: https://github.com/amcintosh/PushOverflow
Download-URL: https://github.com/amcintosh/PushOverflow/archive/refs/tags/2.0.1.tar.gz
Author: Andrew McIntosh
Author-email: andrew@amcintosh.net
License: MIT
Keywords: stackexchange,pushover,notifications
Classifier: Development Status :: 5 - Production/Stable
Classifier: Intended Audience :: Developers
Classifier: Intended Audience :: End Users/Desktop
Classifier: License :: OSI Approved :: MIT License
Classifier: Natural Language :: English
Classifier: Programming Language :: Python
Classifier: Programming Language :: Python :: 3
Classifier: Programming Language :: Python :: 3 :: Only
Classifier: Programming Language :: Python :: 3.8
Classifier: Programming Language :: Python :: 3.9
Classifier: Programming Language :: Python :: 3.10
Classifier: Programming Language :: Python :: 3.11
Classifier: Programming Language :: Python :: 3.12
Classifier: Programming Language :: Python :: 3.13
License-File: LICENSE
Requires-Dist: click<9.0
Requires-Dist: requests<3.0
